piapy/__init__.py
piapy/piapy.py
test/__init__.py
test/test_piapy.py
piapy-0.2.0.dist-info/LICENSE
piapy-0.2.0.dist-info/METADATA
piapy-0.2.0.dist-info/WHEEL
piapy-0.2.0.dist-info/top_level.txt
piapy-0.2.0.dist-info/RECORD
