Metadata-Version: 2.1
Name: piapy
Version: 0.2.0
Summary: Python wrapper for PIA VPN desktop client command line interface
Home-page: https://github.com/bskapital/piapy
Author: Javier Garcia
Author-email: javier.garcia.d@gmail.com
License: UNKNOWN
Platform: UNKNOWN
Classifier: Programming Language :: Python :: 3
Classifier: License :: OSI Approved :: MIT License
Classifier: Operating System :: OS Independent
Requires-Python: >=3.7
